video_descrambler/__init__.py
video_descrambler/cli.py
video_descrambler/distance_calculation.py
video_descrambler/feature_extraction.py
video_descrambler/sequencing.py
video_descrambler/video_descrambler.py
video_descrambler-1.0.0.dist-info/METADATA
video_descrambler-1.0.0.dist-info/WHEEL
video_descrambler-1.0.0.dist-info/entry_points.txt
video_descrambler-1.0.0.dist-info/licenses/LICENSE.md
video_descrambler-1.0.0.dist-info/RECORD
