Metadata-Version: 2.4
Name: video-descrambler
Version: 1.0.0
Summary: Reconstructs corrupted video files where all frames have been shuffled and new frames have been introduced
Author-email: Thibaut Vercueil <thibaut.vercueil@proton.me>
License-File: LICENSE.md
Requires-Python: >=3.12
Requires-Dist: fast-tsp>=0.1.4
Requires-Dist: numpy>=2.2.6
Requires-Dist: opencv-python-headless>=4.12.0.88
Requires-Dist: scikit-learn>=1.7.2
Requires-Dist: typer>=0.20.0
